{
    "language": "ja",
    "daily_theater_id": 1000693,
    "year": 2021,
    "month": 12,
    "day": 26,
    "title": "パーティの後は……？",
    "detail_text": "<:th_ch0007/>あ、見て見て、この写真<:dt_line_end/><:th_ch0102/>あははっ、千歌ちゃんの顔～！このときすっごく喜んでたよね<:dt_line_end/><:th_ch0007/>うん。クリスマス限定のスクールアイドルグッズが当たったんだよねえ<:dt_line_end/><:th_ch0102/>そうそう。沼津ではどこも売り切れちゃって残念がってたから<:dt_line_end/><:th_ch0007/>じゃあこれは一番最初に入れてあげよう<:dt_line_end/><:th_ch0102/>クリスマスパーティのアルバムの一番最初を飾るにふさわしいかも！<:dt_line_end/><:th_ch0007/>楽しいパーティの思い出やね♪<:dt_line_end/><:th_ch0102/>ねえ希さん、この写真も見て。にこさん特製の大盛り唐揚げ！すごい量だったのにあっという間になくなっちゃったよね<:dt_line_end/><:th_ch0007/>カナちゃんのケーキもすぐに完食しちゃって……。ほら、この写真の穂乃果ちゃん見て。ケーキを前に満面の笑顔！<:dt_line_end/><:th_ch0102/>あ～、パーティ楽しかったねえ。はやくアルバム整理してみんなに見てもらおう！<:dt_line_end/>"
}