{
    "language": "ja",
    "daily_theater_id": 1000071,
    "year": 2020,
    "month": 4,
    "day": 13,
    "title": "はあ、かわいい……",
    "detail_text": "<:th_ch0109/>それでね、彼方さん、もぐもぐ……<:dt_line_end/><:th_ch0206/>うんうん、なあに？　ゆっくりでいいよ～。あ、これもお食べ～<:dt_line_end/><:th_ch0109/>わあっ、スイートポテトだあ～！！　ルビィ、これ大好き……はむっ<:dt_line_end/><:th_ch0206/>うんうん、ダイヤちゃんに聞いた～<:dt_line_end/><:th_ch0109/>何話してたっけ？　えっとね……<:dt_line_end/><:th_ch0206/>衣装のことだよね？<:dt_line_end/><:th_ch0109/>あ、そうだった。あのね、次の衣装のスパンコールなんだけど、いろんな色をランダムに混ぜて散りばめるのと、最初からオーロラのやつを縫い付けるの、どっちがいいかなあ？　もぐもぐ……<:dt_line_end/><:th_ch0206/>彼方ちゃんは、ルビィちゃんがいいと思う方でいいと思うな。だって、今までのAqoursの衣装、どれもみーんなすっごく素敵だもん。ルビィちゃんと曜ちゃんがいいと思うものは、Aqoursのみんなに絶対に似合うよ。あ、お茶も飲んで～<:dt_line_end/><:th_ch0109/>わ、このお茶、いい香り！<:dt_line_end/><:th_ch0206/>彼方ちゃんオリジナルブレンドだよ～。お土産も用意してるからね♪<:dt_line_end/>"
}