{
    "language": "ja",
    "daily_theater_id": 1000003,
    "year": 2020,
    "month": 2,
    "day": 5,
    "title": "今日は何の日？",
    "detail_text": "<:th_ch0009/>エマ。今日、誕生日でしょ？　おめでとう<:dt_line_end/><:th_ch0208/>わあ、ありがとう、にこちゃん！<:dt_line_end/><:th_ch0009/>誕生日ってことで、これから頑張りたいことを聞かせなさいよ<:dt_line_end/><:th_ch0208/>えっと……みんなに癒しを届ける、すてきなスクールアイドルになりたいな<:dt_line_end/><:th_ch0009/>なるほどね。ってことは、にこみたいなスクールアイドルになりたいのね！<:dt_line_end/><:th_ch0208/>ふふっ。にこちゃんは憧れのスクールアイドルだよ～<:dt_line_end/><:th_ch0208/>あ！<:dt_line_end/><:th_ch0009/>なによ？<:dt_line_end/><:th_ch0208/>今日はにがついつか……「に」と「ご」だから……今日は、にこちゃんの日でもあるね～！<:dt_line_end/><:th_ch0009/>そっ、そうね……！　エマ、なかなかやるじゃない！　クレープ食べに行きましょ。ご馳走してあげる！<:dt_line_end/>"
}