{
    "language": "ja",
    "daily_theater_id": 1000694,
    "year": 2021,
    "month": 12,
    "day": 27,
    "title": "１年の振り返り？",
    "detail_text": "<:th_ch0203/>ルビィさん、動画流すよ<:dt_line_end/><:th_ch0109/>うん！ライブ動画を見直して１年の振り返り……がんばルビィ！<:dt_line_end/><:th_ch0109/>あ、ルビィ、しずくちゃんのこのパフォーマンス大好き！<:dt_line_end/><:th_ch0203/>ありがとう。このときはルビィさんに衣装相談したよね。ほら、リボンの布地が繊細で私がうまく扱えなくって……。ルビィさんが手伝ってくれたでしょ？<:dt_line_end/><:th_ch0109/>ルビィはちょっとお手伝いしただけだよ<:dt_line_end/><:th_ch0203/>ううん。私、ルビィさんのおかげで納得いくまでこだわることができたの。だから衣装もこんなにパフォーマンスが映えるものになって……。本当にありがとうね、ルビィさん！<:dt_line_end/><:th_ch0109/>えへへ……。またなにかあったらお手伝いさせてね！それにしても、ライブ動画を見て今年のパフォーマンスの反省をしようと思ってたけど、見てたらライブしたくてうずうずしちゃう<:dt_line_end/><:th_ch0203/>私も！よかったあ、ルビィさんも同じで。今からライブは無理だけど、よかったらちょっとだけ練習しに行かない？<:dt_line_end/><:th_ch0109/>わあ、行こう行こう！<:dt_line_end/>"
}