{
    "language": "ja",
    "daily_theater_id": 1001056,
    "year": 2022,
    "month": 12,
    "day": 24,
    "title": "買いすぎ注意！？",
    "detail_text": "<:th_ch0211/>ねえ、買い足りないんじゃないかしら？<:dt_line_end/><:th_ch0212/>What’s!? [sic] これだけ買って足りないとかある？<:dt_line_end/><:th_ch0211/>だってチキンしか買ってないわ……。いろんなお野菜が入ってるサラダのほうがおいしいように、いろんなお肉があったほうがいいわよ<:dt_line_end/><:th_ch0212/>OMG. これで十分だろ…<:dt_line_end/><:th_ch0211/>いいえ、足りないわ。 ミアだってクリスマスにチキンはおかしいって思ってるでしょ！？<:dt_line_end/><:th_ch0212/>だって璃奈と歩夢がチキンがいいって言うからさ……<:dt_line_end/><:th_ch0211/>ランジュは知ってるわよ。ミアがターキーが足りないと思ってること……<:dt_line_end/><:th_ch0212/>えっ……<:dt_line_end/><:th_ch0211/>牛肉と豚肉は我慢するわ。でもターキーは買うわよ！<:dt_line_end/><:th_ch0212/>ちょっとうれしいかも……<:dt_line_end/>"
}