{
    "language": "ja",
    "daily_theater_id": 1000027,
    "year": 2020,
    "month": 2,
    "day": 29,
    "title": "お得なうるう年",
    "detail_text": "<:th_ch0004/>今年はうるう年なんですね<:dt_line_end/><:th_ch0001/>お得な年だねー<:dt_line_end/><:th_ch0004/>お得……とは、1日多いことをそのように言っているのですか？<:dt_line_end/><:th_ch0001/>うん！　いつもより1日多くごはんが食べられるし、1日多く寝られるし……<:dt_line_end/><:th_ch0004/>……穂乃果、あなたって人は……！<:dt_line_end/><:th_ch0001/>それに、1日多く、海未ちゃんと過ごせるね！！<:dt_line_end/><:th_ch0004/>！？　ま、まあ……そういうことになりますね……<:dt_line_end/><:th_ch0001/>1日多く海未ちゃんやことりちゃんとも遊べるし、1日多くμ'sのみんなともおしゃべりできるし、本当にお得だよね～<:dt_line_end/><:th_ch0004/>そう言われると、私も、お得だと思えてきました……<:dt_line_end/><:th_ch0001/>あははっ！　じゃあやっぱり、お得な年だね！<:dt_line_end/>"
}