{
    "language": "ja",
    "daily_theater_id": 1000249,
    "year": 2020,
    "month": 10,
    "day": 8,
    "title": "野望のために！",
    "detail_text": "<:th_ch0207/>なるほど……。なんとなく、感覚がつかめてきました。<:br_inline/>鞠莉さん、ありがとうございます<:dt_line_end/><:th_ch0108/>ふふ、英語のことならいつでも聞いて。<:br_inline/>言語って、英語でも日本語でもそうだけど<:br_inline/>「感覚」っていうか「イメージ」を掴むことが大事よ<:dt_line_end/><:th_ch0207/>しかし、その「感覚」や「イメージ」というのは、<:br_inline/>他言語を喋る時には明確に意識しないと、<:br_inline/>和訳にひっぱられそうになるんですよね……<:dt_line_end/><:th_ch0108/>さっきの「Where」の使い方のこと？<:dt_line_end/><:th_ch0207/>そうです。和訳だと「どこ」になるので、<:br_inline/>「日本の首都はどこですか？」を英訳するときに「Where」を使いたくなりますが、<:br_inline/>これは都市名を答える文になるので、「What」を使わなくてはいけないのですよね。<:br_inline/>和訳だけを考えると間違えやすいです<:dt_line_end/><:th_ch0108/>たしかにそれはそうなんだけど……結局、会話って楽しめたら正解なのよ。<:br_inline/>だから、テストじゃなければ意味がわかればオッケー！<:dt_line_end/><:th_ch0207/>はい！<:dt_line_end/><:th_ch0108/>でも、せっちゃんって成績はいいほうでしょ？<:br_inline/>それなのにまだ勉強したいなんてすごいわね～<:dt_line_end/><:th_ch0207/>ええ。私の「大好きを広める」という野望には海外も含まれているので、<:br_inline/>英語はもちろん、その他の言葉も学びたいんです！<:br_inline/>いろんな言葉で「大好き」を叫びたい！<:dt_line_end/><:th_ch0108/>ワオ！　だったらマリー、力の限りサポートするわ。<:br_inline/>せっちゃんの野望を叶えましょう～！<:dt_line_end/>"
}