{
    "language": "ko",
    "daily_theater_id": 1000778,
    "year": 2022,
    "month": 3,
    "day": 21,
    "title": "春暁",
    "detail_text": "<:th_ch0206/>ん～、いいお天気だな～。お昼寝日和～。あ、かすみちゃん！<:dt_line_end/><:th_ch0202/>あれー、彼方先輩どうしたんですか？お休みですよ？<:dt_line_end/><:th_ch0206/>それはかすみちゃんもでしょ。彼方ちゃんはちょっと練習してからお昼寝を楽しもうかな～って思って部室にきたの<:dt_line_end/><:th_ch0202/>練習するなら、一緒にやりませんか？かすみん、今ランニング終わったところなんですよ。これからダンスの練習しようと思ってるんです<:dt_line_end/><:th_ch0206/>うん……と、言いたいんだけど、お天気が良すぎるから、ちょ～っとだけお昼寝しない？風も気持ちいいしさ～<:dt_line_end/><:th_ch0202/>えー、かすみん眠くないですよ<:dt_line_end/><:th_ch0206/>春眠暁を覚えず、って言うでしょ？ポカポカの中にいたら誰でも眠くなっちゃうよ～<:dt_line_end/><:th_ch0202/>そうですかねえ<:dt_line_end/><:th_ch0206/>春眠暁を覚えず、の続き教えてあげる。「春眠暁を覚えず、処処啼鳥を聞く、夜来風雨の声、花落つること知る多少」<:dt_line_end/><:th_ch0202/>すやあ～<:dt_line_end/>"
}