{
    "language": "ko",
    "daily_theater_id": 1000868,
    "year": 2022,
    "month": 6,
    "day": 19,
    "title": "全力投球！",
    "detail_text": "<:th_ch0205/>ううう〜！！<:dt_line_end/><:th_ch0201/>愛ちゃん、どうしたの？ お腹痛い？<:dt_line_end/><:th_ch0205/>お腹は大丈夫。でも愛さんピンチだよ〜！<:dt_line_end/><:th_ch0201/>ええ！？ 何があったの！？<:dt_line_end/><:th_ch0205/>やりたいことがありすぎて時間が足りないのー！ねえねえ歩夢、これ見て。どう優先順位つけたらいい？<:dt_line_end/><:th_ch0201/>わ……ほんとにたくさんあるね。ランニングコース新規開拓、ライブ演出の案出し、愛トモミーティング、ダジャレショー、衣装作り、もんじゃ新メニュー……<:dt_line_end/><:th_ch0205/>歩夢は何から手につけよ〜、って悩むことない？<:dt_line_end/><:th_ch0201/>私だってあるよ。かわいい衣装デザインを考えたいし、新しいステップも覚えたいし、お手紙のお返事も書きたいし。愛ちゃんと同じくライブの演出だって体力作りだってしたい<:dt_line_end/><:th_ch0205/>なるほど……。愛さん、悟った。こりゃ悩むだけ無駄だわ。悩んでる暇があったら端からやらないと全部できない！よし、歩夢！ まずは体力作り！ 愛さんと一緒にランニングコースの新規開拓しよ！<:dt_line_end/><:th_ch0201/>わかった！ じゃあ練習着に着替えてくるね！<:dt_line_end/>"
}