{
    "language": "ko",
    "daily_theater_id": 1000348,
    "year": 2021,
    "month": 1,
    "day": 15,
    "title": "確実な一歩",
    "detail_text": "<:th_ch0004/>絵里、次の曲の振り付けで相談したいことがあるんですが……<:dt_line_end/><:th_ch0002/>振り付け？　わかりにくいところでもあった？<:dt_line_end/><:th_ch0004/>いえ、ちゃんとできているか見てほしいのです<:dt_line_end/><:th_ch0002/>ちゃんと、って……。海未はいつも完璧じゃない<:dt_line_end/><:th_ch0004/>振りを覚える、ということには自信があるのですが……。<:br_inline/>この前のライブの映像を見ていたら、このままではいけないと思いまして<:dt_line_end/><:th_ch0002/>なるほどね。他の子の上達ぶりが気になった、ってところかしら？<:dt_line_end/><:th_ch0004/>！　そうです！　凛は細かい動きも揃うようになってきましたし、<:br_inline/>ことりもパフォーマンス中の表情が柔らかくなっていました。<:br_inline/>真姫も花陽もどんどんよくなっていて……<:dt_line_end/><:th_ch0002/>私から見たら、海未だって十分成長していると思うわ。<:br_inline/>ポーズも恥ずかしがることはなくなったし、何より楽しそうで<:dt_line_end/><:th_ch0004/>ええ！？　そ、そうでしょうか……<:dt_line_end/><:th_ch0002/>そうよ！　でも、向上心があるのはすばらしいことよ。<:br_inline/>気になるところ、見てあげる。<:br_inline/>その代わり私の練習にも付き合ってね<:dt_line_end/>"
}