{
    "language": "ko",
    "daily_theater_id": 1000325,
    "year": 2020,
    "month": 12,
    "day": 23,
    "title": "頼もしい仲間！",
    "detail_text": "<:th_ch0007/>うーん……これ間に合うかな、ダメかな～？<:br_inline/>ウチとしたことが……<:dt_line_end/><:th_ch0109/>希さん……！<:dt_line_end/><:th_ch0007/>え？　なあに、ルビィちゃん？<:dt_line_end/><:th_ch0109/>口じゃなくて、手を動かすの！！<:dt_line_end/><:th_ch0007/>ええっ！？　ど、どうしたの……？　顔が怖いけど……<:dt_line_end/><:th_ch0109/>手作りブローチ、μ'sのみんなにプレゼントしたいんでしょう？<:dt_line_end/><:th_ch0007/>う、うん……<:dt_line_end/><:th_ch0109/>なら大丈夫！　計画より遅れちゃったかもしれないけど、<:br_inline/>ルビィが手伝うから絶対に間に合わせよう！<:dt_line_end/><:th_ch0007/>ルビィちゃん、頼もしいなあ……。<:br_inline/>うん、そうやね。まだ時間はある！<:dt_line_end/><:th_ch0109/>その意気だよ。<:br_inline/>急ぐけど、気持ちを込めて丁寧に！　頑張ろう～！！<:dt_line_end/>"
}