{
    "language": "ko",
    "daily_theater_id": 1000584,
    "year": 2021,
    "month": 9,
    "day": 8,
    "title": "まだまだ酷暑！",
    "detail_text": "<:th_ch0106/>クックっク……。９月になったっていうのにこの暑さ……ヨハネの魔力が強すぎて、季節さえも狂わせてしまうのね……<:dt_line_end/><:th_ch0109/>善子ちゃん、顔真っ赤だよ？大丈夫？<:dt_line_end/><:th_ch0106/>ヨハネでしょ。顔真っ赤にもなるわよ、この暑さ！なんなのよ！<:dt_line_end/><:th_ch0109/>自分の魔力のせい……って、言ってたけど、違うの？<:dt_line_end/><:th_ch0106/>ちっ……違わない……わよ<:dt_line_end/><:th_ch0109/>ルビィはもう暑くてダメだよ～。ねえ、アイス買いに行かない？<:dt_line_end/><:th_ch0106/>あ、いいわね！<:dt_line_end/><:th_ch0109/>それで、花丸ちゃんの家に行こうよ。花丸ちゃんのおうちは木が多くて風が気持ちいいし<:dt_line_end/><:th_ch0106/>じゃあ私、電話するわ。アイス何がいいのか聞いておくわね<:dt_line_end/><:th_ch0109/>あ、のっぽパンがいるかも聞いて！<:dt_line_end/>"
}