{
    "language": "zh",
    "daily_theater_id": 1000237,
    "year": 2020,
    "month": 9,
    "day": 26,
    "title": "親愛なるあなたへ５",
    "detail_text": "<:th_ch0001/>ビデオメッセージ、私たちの番だよ。２人とも準備はいいかな？<:dt_line_end/><:th_ch0101/>まかせて！　カメラの準備もオッケーだよ〜<:dt_line_end/><:th_ch0201/>あの、私からでもいいかな？<:dt_line_end/><:th_ch0001/>いいよいいよ、じゃあ撮るからね〜<:dt_line_end/><:th_ch0201/>いつも私の隣で見守ってくれて、本当にありがとう。<:br_inline/>あなたがスクールアイドルに誘ってくれたときはビックリしたけど、<:br_inline/>今は本当に、毎日が楽しいの。穂乃果ちゃんや千歌ちゃんたちとも友達になれて、<:br_inline/>いろんなことを教えあったりして、私たち全員、<:br_inline/>もっともっとみんなを幸せにできるスクールアイドルになりたいって思ってるよ<:dt_line_end/><:th_ch0201/>でも、それって私たちだけじゃできないことなの。<:br_inline/>あなたがそばで応援してくれないと、不安なんだよ……。<:br_inline/>あなたがサポートしてくれて、応援して、笑顔でいてくれないと、私、いやなの。<:br_inline/>だから、これからもずっとずっと一緒だよ！<:dt_line_end/><:th_ch0101/>歩夢ちゃんの言う通り！　私たちみんな同じ気持ちだよ。<:br_inline/>あなたが初めて内浦にきてくれたときのこと、今もすっごくよく覚えてる。<:br_inline/>初めてのときから、あなたにはいろんなことを手伝ってもらったし、<:br_inline/>あなたがいてくれたからこそ気づけたこともあるんだ<:dt_line_end/><:th_ch0101/>あなたはどうかなあ？　私たちと一緒にいることで、なにかいいことあった？<:br_inline/>あなたはいつも親切だから甘えちゃうんだけど、<:br_inline/>私たちもあなたのためになにかしたいなあ……そうだ！<:br_inline/>あなたも私にわがままを言ってよ！　私、なーんでもきいちゃうよ！<:dt_line_end/><:th_ch0201/>ふふっ、千歌ちゃん、あの子結構わがままなとこあるから、<:br_inline/>お願いなんでもきくと疲れちゃうかもしれないよ。<:dt_line_end/><:th_ch0101/>えー、難しいお願いのほうがききがいがあるよねえ、穂乃果ちゃん<:dt_line_end/><:th_ch0001/>それはそうかも。高い壁ほど乗り越えがいがあるー！<:dt_line_end/><:th_ch0001/>あのねあのね、あなたの応援って、あなたが思ってる以上に私たちにとって大切なの！<:br_inline/>だって、それが私たちのパワーの源なんだもん。<:br_inline/>あんこがないとさみしいお饅頭になっちゃうでしょ？<:br_inline/>それと同じで、あなたの応援がないと、私たちの全力がパワーダウンしちゃう。<:br_inline/>応援があると、パワーアップするの！<:dt_line_end/><:th_ch0001/>だからこれからも、私たちに頑張れーって言って欲しい。<:br_inline/>私たち、絶対にそれに応えるから！　あ、あともう一つ。<:br_inline/>頑張れーって言うのは、一番そばでお願いね♪<:dt_line_end/><:th_ch0101/>あ！　私、言い忘れちゃったことがある〜！<:dt_line_end/><:th_ch0201/>私も、これからもよろしくねって言い忘れちゃった……<:dt_line_end/><:th_ch0001/>うわあ！　私も！　あ、ねえねえ、じゃあ最後に３人で言おうよ！<:br_inline/>いくよ〜……<:dt_line_end/><:th_ch0001/>これからもよろしくね！！<:dt_line_end/><:th_ch0101/>これからもよろしくね！！<:dt_line_end/><:th_ch0201/>これからもよろしくね！！<:dt_line_end/>"
}