{
    "language": "zh",
    "daily_theater_id": 1000820,
    "year": 2022,
    "month": 5,
    "day": 2,
    "title": "上げていこう！",
    "detail_text": "<:th_ch0001/>おはよ〜、にこちゃん...<:dt_line_end/><:th_ch0009/>なによ、元気ないわね……<:dt_line_end/><:th_ch0001/>にこちゃんだってそうじゃん～<:dt_line_end/><:th_ch0009/>あったりまえじゃない！ GWだってのになんで勉強しに来なきゃいけないのよ！<:dt_line_end/><:th_ch0001/>わかる！ おまけで休みにしてくれたっていいのにね！<:dt_line_end/><:th_ch0009/>はあ〜。こうなったら気分を上げるしかないわね<:dt_line_end/><:th_ch0001/>どうするの？ アルパカなでに行く？<:dt_line_end/><:th_ch0009/>アルパカをなでるくらいじゃダメよ。なでには行くけど。放課後、スクールアイドルDVDマラソンをするわよ！<:dt_line_end/><:th_ch0001/>おお〜、いいね！ 私もやりたい！<:dt_line_end/><:th_ch0009/>全員呼ぶわよ～！<:dt_line_end/>"
}