{"language":"zh","daily_theater_id":1001054,"year":2022,"month":12,"day":22,"title":"あなたに贈るカード","detail_text":"\u003c:th_ch0101/\u003e真っ赤なおっはっなっの～𝅘𝅥𝅮\u003c:dt_line_end/\u003e\u003c:th_ch0004/\u003eご機嫌ですね、千歌\u003c:dt_line_end/\u003e\u003c:th_ch0101/\u003eあ、海未ちゃん！ ねえねえ、みんなに渡すカード描いてるんだけど、どう？\u003c:dt_line_end/\u003e\u003c:th_ch0004/\u003e見たくないです！\u003c:dt_line_end/\u003e\u003c:th_ch0101/\u003eえー！？\u003c:dt_line_end/\u003e\u003c:th_ch0004/\u003e先に見てしまったらネタバレになってしまうではありませんか。楽しみにさせてください。\u003c:dt_line_end/\u003e\u003c:th_ch0101/\u003eあ、それもそっか。へへへ、ごめんね。ねえねえ、クリスマス雪降るかな～\u003c:dt_line_end/\u003e\u003c:th_ch0004/\u003eどうでしょう、統計的にホワイトクリスマスというのはそう多くないと聞きますが……\u003c:dt_line_end/\u003e\u003c:th_ch0101/\u003eホワイトクリスマスだったら今作ってるカード……\u003c:dt_line_end/\u003e\u003c:th_ch0004/\u003eダメダメ！ ネタバレは禁止ですー！ 楽しみが減っちゃいます！\u003c:dt_line_end/\u003e"}