{
    "language": "zh",
    "daily_theater_id": 1000501,
    "year": 2021,
    "month": 6,
    "day": 17,
    "title": "一度やってみたかったんです",
    "detail_text": "<:th_ch0202/>えっと、まずはスマホでこのアプリをダウンロードしてください<:dt_line_end/><:th_ch0104/>これですね……はい、ダウンロードできました<:dt_line_end/><:th_ch0202/>OKです！　それじゃあ、このアプリを起動して、カメラで写真を撮る！<:br_inline/>ダイヤ先輩、いきますよ～、はいチーズ！<:dt_line_end/><:th_ch0104/>ちょ、かすみさん！　カメラを向けるのが突然すぎます！<:br_inline/>変な顔になっているのでは……<:dt_line_end/><:th_ch0202/>大丈夫です。ちゃんと可愛く撮れてます。<:br_inline/>それで撮った写真をこうして、こうして～……じゃん！<:br_inline/>こんな感じでどうですか？<:dt_line_end/><:th_ch0104/>わたくしの写真に猫耳が……！<:dt_line_end/><:th_ch0202/>ふっふっふ、猫耳だけじゃなくて、写真にスタンプを押したり、<:br_inline/>絵をかいたりすることもできるんですよ<:dt_line_end/><:th_ch0104/>なるほど、写真を可愛くするのはこういう風にすればよいのですね<:dt_line_end/><:th_ch0202/>はい、覚えれば簡単です！<:br_inline/>だからルビ子と２人で撮った写真だってすぐに可愛くできると思いますよ、<:br_inline/>ダイヤ先輩♪<:dt_line_end/><:th_ch0104/>なっ、なんでバレて……！？　うう、ありがとうございます<:dt_line_end/>"
}