{"language":"zh","daily_theater_id":1001118,"year":2023,"month":2,"day":24,"title":"釣り堀にて","detail_text":"\u003c:th_ch0008/\u003eお魚、釣れないね〜\u003c:dt_line_end/\u003e\u003c:th_ch0108/\u003e釣り堀って必ず釣れるってわけじゃないのねえ\u003c:dt_line_end/\u003e\u003c:th_ch0008/\u003eあっ……\u003c:dt_line_end/\u003e\u003c:th_ch0108/\u003eきた！？\u003c:dt_line_end/\u003e\u003c:th_ch0008/\u003e餌だけ取られちゃったみたい……\u003c:dt_line_end/\u003e\u003c:th_ch0108/\u003e頭のいい魚ばっかりなのね、ここ\u003c:dt_line_end/\u003e\u003c:th_ch0008/\u003eもっといっぱい連れて楽しいかな、って思ったんだけど、ごめんね……\u003c:dt_line_end/\u003e\u003c:th_ch0108/\u003eマリーは楽しいわよ？\u003c:dt_line_end/\u003e\u003c:th_ch0008/\u003eえ？\u003c:dt_line_end/\u003e\u003c:th_ch0108/\u003e釣りってお友達とのおしゃべりをゆっくり楽しむ時間でもあると思うのよね。マリーたちも海釣りをしたりするんだけど、釣れない日でもつまらなかったって思ったことないもの〜！\u003c:dt_line_end/\u003e\u003c:th_ch0008/\u003eそうなんだ……おしゃべりを楽しむ時間かあ……\u003c:dt_line_end/\u003e\u003c:th_ch0108/\u003eそうよ〜！\u003c:dt_line_end/\u003e\u003c:th_ch0008/\u003eじゃあ、鞠莉さんが好きなスクールアイドルのお話を聞きたいな！\u003c:dt_line_end/\u003e\u003c:th_ch0108/\u003eその話をすると夜までかかっちゃうわよ。覚悟してね𝅘𝅥𝅮\u003c:dt_line_end/\u003e"}