{
    "language": "zh",
    "daily_theater_id": 1000397,
    "year": 2021,
    "month": 3,
    "day": 5,
    "title": "負けない！",
    "detail_text": "<:th_ch0009/>やるわね、ルビィ……<:dt_line_end/><:th_ch0109/>にこさんこそ……<:dt_line_end/><:th_ch0009/>スクールアイドルDVDマラソン、休憩なしでついてこれたのは<:br_inline/>花陽以外じゃルビィが初めてよ。見所あるじゃない<:dt_line_end/><:th_ch0109/>ルビィ、スクールアイドルに関してなら自信があるの！<:br_inline/>これはにこさんにも花陽ちゃんにも負けないよ！<:dt_line_end/><:th_ch0009/>大きくでたわね！<:dt_line_end/><:th_ch0109/>その証拠に……これ、見て<:dt_line_end/><:th_ch0009/>こっ……これは！？<:dt_line_end/><:th_ch0109/>雑誌の切り抜きをスクラップして作った、スクールアイドル図鑑！<:dt_line_end/><:th_ch0009/>すごい……すごいじゃない！<:br_inline/>全国のスクールアイドルの情報がまとめられてるわ！<:dt_line_end/><:th_ch0109/>これで終わりじゃないの……<:br_inline/>ここに載せきれなかった情報を集めた、スクールアイドル図鑑パート２！！<:dt_line_end/><:th_ch0009/>あんた、本当に見所があるわね！<:br_inline/>これがあればいくらでもスクールアイドルについて語れるわ！　語りましょう！<:dt_line_end/>"
}