{
    "language": "zh",
    "daily_theater_id": 1000648,
    "year": 2021,
    "month": 11,
    "day": 11,
    "title": "プレゼント作り",
    "detail_text": "<:th_ch0206/>ねえねえ、ことりちゃん、これ変じゃないかな？<:dt_line_end/><:th_ch0003/>大丈夫。変じゃないよ<:dt_line_end/><:th_ch0206/>でもこことか、もう少し直したほうがよくない？着た時に動きにくくないかな？<:dt_line_end/><:th_ch0003/>大丈夫！ことりが保証するよ！彼方さんが遥ちゃんのために心を込めて作ったワンピースなんだから、もっと自身持って<:dt_line_end/><:th_ch0206/>うう、今年のお誕生日プレゼント、遥ちゃん喜んでくれるかな～<:dt_line_end/><:th_ch0003/>絶対絶対喜んでくれるよ。私だったら感動して泣いちゃうかも<:dt_line_end/><:th_ch0206/>ことりちゃんがそう言ってくれるなら……！あ～、ことりちゃんにいろいろ相談してよかった！ワンピース作りのお手伝いも本当にありがとう！<:dt_line_end/><:th_ch0003/>私の方こそすてきなワンピースづくりのお手伝いができて嬉しいかったよ。ほらほら、もう行かなきゃ。プレゼントを見た遥ちゃんのお話、また聞かせてね<:dt_line_end/><:th_ch0206/>うん！報告する！あと、今度あらためてお礼させてね。彼方ちゃん、なんでもしちゃう～<:dt_line_end/><:th_ch0003/>わあ、本当！？じゃあ私、彼方さんの手作りのお弁当がいいな！<:dt_line_end/>"
}